Darling_Instagram/Darling.py
Darling_Instagram/__init__.py
darlingvip_instagram-0.0.1.dist-info/METADATA
darlingvip_instagram-0.0.1.dist-info/WHEEL
darlingvip_instagram-0.0.1.dist-info/RECORD
