Metadata-Version: 2.1
Name: DarlingVip-Instagram
Version: 0.0.1
Summary: DO WHAT YOU WANT ON INSTAGRAM!
Author-email: Darling Mquang <quang722008@gmail.com>
Classifier: License :: OSI Approved :: MIT License
Classifier: Operating System :: OS Independent
Classifier: Programming Language :: Python :: 3
Requires-Python: >=3.10
